behatrix/__init__.py
behatrix/__main__.py
behatrix/behatrix_functions.py
behatrix/behatrix_gui.py
behatrix/behatrix_qrc.py
behatrix/behatrix_ui.py
behatrix/please_wait.svg
behatrix/version.py
behatrix-0.13.dist-info/licenses/LICENSE.TXT
behatrix-0.13.dist-info/METADATA
behatrix-0.13.dist-info/WHEEL
behatrix-0.13.dist-info/entry_points.txt
behatrix-0.13.dist-info/top_level.txt
behatrix-0.13.dist-info/RECORD
