Metadata-Version: 2.4
Name: behatrix
Version: 0.13
Summary: Behatrix - Behavioral Sequences Analysis with permutation test
Author-email: Olivier Friard <olivier.friard@unito.it>
License:                     GNU GENERAL PUBLIC LICENSE
Project-URL: Homepage, http://www.boris.unito.it/behatrix
Project-URL: Documentation, https://github.com/olivierfriard/behatrix/blob/master/README.rst
Project-URL: Change_log, https://github.com/olivierfriard/behatrix/wiki/revision-history
Project-URL: Source_code, https://github.com/olivierfriard/behatrix
Project-URL: Issues, https://github.com/olivierfriard/behatrix/issues
Classifier: Operating System :: OS Independent
Classifier: Intended Audience :: Science/Research
Classifier: Intended Audience :: Education
Classifier: Programming Language :: Python :: 3.10
Classifier: Programming Language :: Python :: 3.11
Classifier: Programming Language :: Python :: 3.12
Classifier: License :: OSI Approved :: GNU General Public License v3 (GPLv3)
Classifier: Topic :: Scientific/Engineering
Classifier: Topic :: Scientific/Engineering :: Visualization
Classifier: Operating System :: OS Independent
Requires-Python: >=3.10
License-File: LICENSE.TXT
Requires-Dist: numpy
Requires-Dist: pyside6
Requires-Dist: shiboken6>=6.8.0.1
Dynamic: license-file
